opengenai/__init__.py
opengenai/embed_search.py
opengenai/html_parser.py
opengenai/search.py
opengenai/search_tool.py
opengenai-0.1.3.dist-info/LICENSE
opengenai-0.1.3.dist-info/METADATA
opengenai-0.1.3.dist-info/WHEEL
opengenai-0.1.3.dist-info/top_level.txt
opengenai-0.1.3.dist-info/RECORD
